{
  "_id": "69325b507cd59da087ad2912",
  "name": "SOCOM Armory",
  "surname": "Armory",
  "nickname": "SOCOM",
  "firstname": "SOCOM",
  "location": "Customs",
  "description": "DevGru SOCOM JSOC Armory",
  "avatar": "/files/trader/avatar/socom.png",
  "availableInRaid": false,
  "balance_dol": 500000,
  "balance_eur": 0,
  "balance_rub": 0,
  "buyer_up": false,
  "currency": "USD",
  "customization_seller": false,
  "discount": 0,
  "discount_end": 0,
  "gridHeight": 160,
  "insurance": {
    "availability": false,
    "excluded_category": [],
    "max_return_hour": 36,
    "max_storage_time": 72,
    "min_payment": 0,
    "min_return_hour": 24
  },
  "items_buy": {
    "category": [],
    "id_list": []
  },
  "items_buy_prohibited": {
    "category": [],
    "id_list": []
  },
  "loyaltyLevels": [
    {
      "buy_price_coef": 88,
      "exchange_price_coef": 0,
      "heal_price_coef": 0,
      "insurance_price_coef": 21,
      "minLevel": 10,
      "minSalesSum": 0,
      "minStanding": 0.0,
      "repair_price_coef": 210
    },
    {
      "buy_price_coef": 86,
      "exchange_price_coef": 0,
      "heal_price_coef": 0,
      "insurance_price_coef": 19,
      "minLevel": 17,
      "minSalesSum": 25000,
      "minStanding": 0.29,
      "repair_price_coef": 180
    },
    {
      "buy_price_coef": 84,
      "exchange_price_coef": 0,
      "heal_price_coef": 0,
      "insurance_price_coef": 17,
      "minLevel": 27,
      "minSalesSum": 50000,
      "minStanding": 0.35,
      "repair_price_coef": 175
    },
    {
      "buy_price_coef": 82,
      "exchange_price_coef": 0,
      "heal_price_coef": 0,
      "insurance_price_coef": 15,
      "minLevel": 37,
      "minSalesSum": 100000,
      "minStanding": 0.44,
      "repair_price_coef": 165
    }
  ],
  "medic": false,
  "nextResupply": 1631489718,
  "repair": {
    "availability": true,
    "currency": "5696686a4bdc2da3298b456a",
    "currency_coefficient": 1,
    "excluded_category": [],
    "excluded_id_list": [],
    "price_rate": 0,
    "quality": "0.85"
  },
  "sell_category": [
    "82e7fac0b7495d72d4083356",
    "ac705d3440c1407645e33579",
    "dc97aee367144dc03389405d",
    "7ffcc96aa06c7e90940330c5",
    "e8f46e3ad74b9d862121f9dc",
    "5b47574386f77428ca22b33e",
    "5b47574386f77428ca22b33f",
    "5b5f78dc86f77409407a7f8e",
    "5b47574386f77428ca22b346",
    "5b47574386f77428ca22b340",
    "5b47574386f77428ca22b344",
    "5b47574386f77428ca22b342",
    "5b47574386f77428ca22b341",
    "5b47574386f77428ca22b345",
    "5b47574386f77428ca22b343",
    "5b5f71b386f774093f2ecf11",
    "5b5f71c186f77409407a7ec0",
    "5b5f71de86f774093f2ecf13",
    "5b5f724186f77447ed5636ad",
    "5b5f736886f774094242f193",
    "5b5f73ec86f774093e6cb4fd",
    "5b5f74cc86f77447ec5d770a",
    "5b5f750686f774093e6cb503",
    "5b5f751486f77447ec5d770c",
    "5b5f752e86f774093e6cb505",
    "5b5f754a86f774094242f19b",
    "5b5f755f86f77447ec5d770e",
    "5b5f757486f774093e6cb507",
    "5b5f75b986f77447ec5d7710",
    "5b5f75c686f774094242f19f",
    "5b5f75e486f77447ec5d7712",
    "5b5f760586f774093e6cb509",
    "5b5f761f86f774094242f1a1",
    "575146b724597720a27126d5",
    "635a758bfefc88a93f021b8a",
    "55d45d3f4bdc2d972f8b456c",
    "5b363dd25acfc4001a598fd2",
    "5d1b36a186f7742523398433",
    "59e3577886f774176a362503",
    "5d6e67fba4b9361bc73bc779",
    "5b5f764186f77447ec5d7714"
  ],
  "sell_modifier_for_prohibited_items": 0,
  "unlockedByDefault": false
}
